ckapy/__init__.py
ckapy/date_string.py
ckapy/loop_progress.py
ckapy/print_uncertainty.py
ckapy-1.0.0.dist-info/licenses/LICENCE
ckapy-1.0.0.dist-info/METADATA
ckapy-1.0.0.dist-info/WHEEL
ckapy-1.0.0.dist-info/top_level.txt
ckapy-1.0.0.dist-info/RECORD
