Metadata-Version: 2.4
Name: CKaPy
Version: 1.0.0
Summary: A collection of tools from my Ph.D. in physics.
Author-email: Connor Kapahi <connorkapahi@gmail.com>
License-Expression: MIT
Project-URL: Homepage, https://github.com/ckapahi/ckapy
Project-URL: Issues, https://github.com/ckapahi/ckapy/issues
Classifier: Programming Language :: Python
Classifier: Programming Language :: Python :: 3
Requires-Python: >=3.9
License-File: LICENCE
Requires-Dist: numpy>=1.0.0
Dynamic: license-file
